textual_paint/__init__.py
textual_paint/action.py
textual_paint/ansi_art_document.py
textual_paint/args.py
textual_paint/ascii_borders.py
textual_paint/ascii_mode.py
textual_paint/auto_restart.py
textual_paint/canvas.py
textual_paint/char_input.py
textual_paint/character_picker.py
textual_paint/colors_box.py
textual_paint/edit_colors.py
textual_paint/enhanced_directory_tree.py
textual_paint/export_templates.py
textual_paint/figlet_font_writer.py
textual_paint/file_dialogs.py
textual_paint/gallery.css
textual_paint/gallery.py
textual_paint/graphics_primitives.py
textual_paint/icons.py
textual_paint/inspector.py
textual_paint/launch_editor.py
textual_paint/menus.py
textual_paint/meta_glyph_font.py
textual_paint/paint.css
textual_paint/paint.py
textual_paint/palette_data.py
textual_paint/py.typed
textual_paint/rasterize_ansi_art.py
textual_paint/scrollbars.py
textual_paint/stretch_skew_icons.ans
textual_paint/stretch_skew_icons_full_ascii.ans
textual_paint/stretch_skew_icons_partial_ascii.ans
textual_paint/themed_icon.py
textual_paint/tool.py
textual_paint/toolbox.py
textual_paint/wallpaper.py
textual_paint/windows.py
textual_paint/fonts/NanoTiny/NanoTiny_v14.png
textual_paint/fonts/NanoTiny/NanoTiny_v14_2x2.flf
textual_paint/fonts/NanoTiny/NanoTiny_v14_4x4.flf
textual_paint/fonts/NanoTiny/NanoTiny_v14_no_border.png
textual_paint/fonts/NanoTiny/OFL.txt
textual_paint/localization/i18n.py
textual_paint/localization/parse_rc_file.py
textual_paint/localization/preprocess.py
textual_paint/localization/__pycache__/localizations.js
textual_paint/localization/ar/localizations.js
textual_paint/localization/cs/localizations.js
textual_paint/localization/da/localizations.js
textual_paint/localization/de/localizations.js
textual_paint/localization/el/localizations.js
textual_paint/localization/es/localizations.js
textual_paint/localization/fi/localizations.js
textual_paint/localization/fr/localizations.js
textual_paint/localization/he/localizations.js
textual_paint-0.4.0.dist-info/LICENSE.txt
textual_paint-0.4.0.dist-info/METADATA
textual_paint-0.4.0.dist-info/WHEEL
textual_paint-0.4.0.dist-info/entry_points.txt
textual_paint-0.4.0.dist-info/top_level.txt
textual_paint-0.4.0.dist-info/RECORD
