Metadata-Version: 2.1
Name: textual_paint
Version: 0.4.0
Summary: MS Paint in the terminal, built with Textual
Home-page: https://github.com/1j01/textual-paint
Author: Isaiah Odhner
Author-email: isaiahodhner@gmail.com
License: MIT
Project-URL: Source, https://github.com/1j01/textual-paint
Project-URL: Changelog, https://github.com/1j01/textual-paint/blob/main/CHANGELOG.md
Keywords: tui,terminal,paint,drawing,art,graphics,text,textual,rich,ansi,ansi-art,mspaint
Classifier: Environment :: Console
Classifier: Intended Audience :: End Users/Desktop
Classifier: License :: OSI Approved :: MIT License
Classifier: Development Status :: 3 - Alpha
Classifier: Operating System :: OS Independent
Classifier: Programming Language :: Python :: 3.10
Classifier: Topic :: Artistic Software
Classifier: Topic :: Communications :: BBS
Classifier: Topic :: Communications :: Chat :: Internet Relay Chat
Classifier: Topic :: Multimedia :: Graphics :: Editors :: Raster-Based
Classifier: Topic :: Terminals
Classifier: Topic :: Text Editors
Classifier: Natural Language :: Arabic
Classifier: Natural Language :: Chinese (Simplified)
Classifier: Natural Language :: Chinese (Traditional)
Classifier: Natural Language :: Czech
Classifier: Natural Language :: Danish
Classifier: Natural Language :: Dutch
Classifier: Natural Language :: English
Classifier: Natural Language :: Finnish
Classifier: Natural Language :: French
Classifier: Natural Language :: German
Classifier: Natural Language :: Greek
Classifier: Natural Language :: Hebrew
Classifier: Natural Language :: Hungarian
Classifier: Natural Language :: Italian
Classifier: Natural Language :: Japanese
Classifier: Natural Language :: Korean
Classifier: Natural Language :: Norwegian
Classifier: Natural Language :: Polish
Classifier: Natural Language :: Portuguese
Classifier: Natural Language :: Portuguese (Brazilian)
Classifier: Natural Language :: Russian
Classifier: Natural Language :: Slovak
Classifier: Natural Language :: Slovenian
Classifier: Natural Language :: Spanish
Classifier: Natural Language :: Swedish
Classifier: Natural Language :: Turkish
License-File: LICENSE.txt
Requires-Dist: textual ==0.38.1
Requires-Dist: rich ==13.4.2
Requires-Dist: stransi ==0.3.0
Requires-Dist: pyperclip ==1.8.2
Requires-Dist: pyfiglet ==0.8.post1
Requires-Dist: Pillow ==9.5.0
Provides-Extra: dev
Requires-Dist: watchdog ==3.0.0 ; extra == 'dev'
Requires-Dist: psutil ==5.9.0 ; extra == 'dev'
Requires-Dist: types-Pillow ==10.0.0.1 ; extra == 'dev'
Requires-Dist: types-psutil ==5.9.5.15 ; extra == 'dev'
Provides-Extra: wallpaper
Requires-Dist: appscript ==1.2.2 ; extra == 'wallpaper'
Requires-Dist: pyobjc-framework-Quartz ==9.2 ; extra == 'wallpaper'
Requires-Dist: pyxdg ==0.28 ; extra == 'wallpaper'
Requires-Dist: PyGObject ==3.42.1 ; extra == 'wallpaper'
